MANIFEST.in
README.rst
setup.py
django_freeplay.egg-info/PKG-INFO
django_freeplay.egg-info/SOURCES.txt
django_freeplay.egg-info/dependency_links.txt
django_freeplay.egg-info/requires.txt
django_freeplay.egg-info/top_level.txt
freeplay/__init__.py
freeplay/admin.py
freeplay/forms.py
freeplay/models.py
freeplay/settings.py
freeplay/urls_admin.py
freeplay/views.py
freeplay/templates/admin
freeplay/templates/admin/freeplay/_item_delete.html
freeplay/templates/admin/freeplay/_item_form.html
freeplay/templates/admin/freeplay/dashboard.html
freeplay/templates/admin/freeplay/item_delete.html
freeplay/templates/admin/freeplay/item_form.html
freeplay/templatetags/__init__.py
freeplay/templatetags/freeplay_tags.py