Metadata-Version: 1.1
Name: django-freeplay
Version: 0.1.91
Summary: Easily add CMS functionality to your Django site
Home-page: http://github.com/pullswitch/django-freeplay
Author: Dave Lowe
Author-email: dave@hellopullswitch.com
License: MIT
Platform: UNKNOWN
Classifier: Development Status :: 4 - Beta
Classifier: Environment :: Web Environment
Classifier: Intended Audience :: Developers
Classifier: License :: OSI Approved :: MIT License
Classifier: Operating System :: OS Independent
Classifier: Programming Language :: Python
Classifier: Framework :: Django
